<DOMSymbolItem xmlns:xsi="http://www.w3.org/2001/XMLSchema-instance" xmlns="http://ns.adobe.com/xfl/2008/" name="Tween 4" itemID="57fd37bd-0000069c" symbolType="graphic" lastModified="1476212669" lastUniqueIdentifier="5">
  <timeline>
    <DOMTimeline name="Tween 4">
      <layers>
        <DOMLayer name="Layer 1" color="#4F80FF" current="true" isSelected="true">
          <frames>
            <DOMFrame index="0" keyMode="9728">
              <elements>
                <DOMSymbolInstance libraryItemName="Assets/mussel-shadow" selected="true" centerPoint3DX="-419.8" centerPoint3DY="47.2">
                  <matrix>
                    <Matrix a="0.6055908203125" b="-0.13226318359375" c="0.741241455078125" d="0.877716064453125" tx="-521.45" ty="42.35"/>
                  </matrix>
                  <transformationPoint>
                    <Point x="214.1" y="51.05"/>
                  </transformationPoint>
                </DOMSymbolInstance>
                <DOMSymbolInstance libraryItemName="Assets/mussel-shadow" selected="true" centerPoint3DX="-220.5" centerPoint3DY="-96.4">
                  <matrix>
                    <Matrix a="0.39166259765625" b="0.0640716552734375" c="-0.124755859375" d="0.55035400390625" tx="-325.15" ty="-122.5"/>
                  </matrix>
                  <transformationPoint>
                    <Point x="205.25" y="45.95"/>
                  </transformationPoint>
                </DOMSymbolInstance>
                <DOMSymbolInstance libraryItemName="Assets/mussel-shadow" selected="true" centerPoint3DX="192.9" centerPoint3DY="-86.9">
                  <matrix>
                    <Matrix a="0.409698486328125" b="0.0189056396484375" c="0.19219970703125" d="0.567840576171875" tx="103.8" ty="-113.3"/>
                  </matrix>
                  <transformationPoint>
                    <Point x="205.95" y="46.7"/>
                  </transformationPoint>
                </DOMSymbolInstance>
                <DOMSymbolInstance libraryItemName="Assets/mussel-shadow" selected="true" centerPoint3DX="253.5" centerPoint3DY="-81.8">
                  <matrix>
                    <Matrix a="0.33648681640625" b="0.0155487060546875" c="0.129196166992188" d="0.560272216796875" tx="208.15" ty="-90.3"/>
                  </matrix>
                  <transformationPoint>
                    <Point x="205.95" y="46.4"/>
                  </transformationPoint>
                </DOMSymbolInstance>
                <DOMSymbolInstance libraryItemName="Assets/mussel-shadow" selected="true" centerPoint3DX="397.6" centerPoint3DY="20.65">
                  <matrix>
                    <Matrix a="0.536300659179688" b="0.0247344970703125" c="0.201812744140625" d="0.689254760742188" tx="283.4" ty="-5.15"/>
                  </matrix>
                  <transformationPoint>
                    <Point x="206" y="46.65"/>
                  </transformationPoint>
                </DOMSymbolInstance>
              </elements>
            </DOMFrame>
          </frames>
        </DOMLayer>
      </layers>
    </DOMTimeline>
  </timeline>
</DOMSymbolItem>