<DOMSymbolItem xmlns:xsi="http://www.w3.org/2001/XMLSchema-instance" xmlns="http://ns.adobe.com/xfl/2008/" name="Assets/LifecycleAssets/LC_glochidiaCallOut-Fish" itemID="58051b7e-00001ad2" lastModified="1476729726">
  <timeline>
    <DOMTimeline name="LC_glochidiaCallOut-Fish">
      <layers>
        <DOMLayer name="lower jaw" color="#9933CC" locked="true" autoNamed="false">
          <frames>
            <DOMFrame index="0" keyMode="9728">
              <elements>
                <DOMShape isDrawingObject="true">
                  <matrix>
                    <Matrix a="0.787216186523438" tx="840.6" ty="250.6"/>
                  </matrix>
                  <fills>
                    <FillStyle index="1">
                      <SolidColor color="#FFFFFF" alpha="0.407843137254902"/>
                    </FillStyle>
                  </fills>
                  <edges>
                    <Edge fillStyle1="1" edges="!3073 127[3130 158 3155 228!3155 228[3168 263 3169 292!3169 292[3137 539 2453 716!2453 716[2222 776 1950 819!1950 819[1747 851 1650 857!1650 857[1562 860 1477 876!1477 876[1307 910 1318 982!1318 982[1020 1131 619 1048!619 1048[196 959
 0 669!0 669|0 595!0 595[32 620 106 692!106 692[173 757 221 789!221 789[373 895 607 889!607 889[#3A9.7F 879.75 1542 645!1542 645[#622.12 #285.2 1602 642!1602 642[1718 629 1857 583!1857 583[1944 554 2103 488!2103 488|3033.5 107.5!3033.5
 107.5[#BF5.57 #71.27 3073 127"/>
                    <Edge cubics="!3073 127(;3164,176 3169,292 3169,292q3073 127Q3130 158q3155 228Q3168 263q3169 292);"/>
                    <Edge cubics="!3169 292(;3119,680 1815,847 1650,857q3169 292Q3137 539q2453 716Q2222 776q1950 819Q1747 851q1650 857);"/>
                    <Edge cubics="!1650 857(;1649,857 1301,867 1318,982q1650 857Q1562 860q1477 876Q1307 910q1318 982);"/>
                    <Edge cubics="!1318 982(;939,1172 271,1071 0,669q1318 982Q1020 1131q619 1048Q196 959q0 669);"/>
                    <Edge cubics="!0 669(;0,669 0,595 0,595q0 669 0 595);"/>
                    <Edge cubics="!221 789(221,789;322,860 451,893 607,889q221 789Q373 895q607 889)607,889;"/>
                    <Edge cubics="!106 692(;151,735 189,768 221,789q106 692Q173 757q221 789);"/>
                    <Edge cubics="!0 595(;21,612 57,644 106,692q0 595Q32 620q106 692);"/>
                    <Edge cubics="!607 889(;827,883 1138,803 1542,645q607 889Q937 880q1542 645);"/>
                    <Edge cubics="!3034 108(;3052,111 3065,118 3073,127q3034 108Q3061 113q3073 127);"/>
                    <Edge cubics="!1857 583(;1915,564 1997,532 2103,488q1857 583Q1944 554q2103 488);"/>
                    <Edge cubics="!2103 488(;2103,488 3034,108 3034,108q2103 488 3034 108);"/>
                    <Edge cubics="!1542 645(1542,645;1561,645 1581,644 1602,642q1542 645Q1570 645q1602 642);"/>
                    <Edge cubics="!1602 642(;1679,633 1764,614 1857,583q1602 642Q1718 629q1857 583);"/>
                  </edges>
                </DOMShape>
              </elements>
            </DOMFrame>
          </frames>
        </DOMLayer>
        <DOMLayer name="fish outline" color="#FF4FFF" locked="true" current="true" isSelected="true" autoNamed="false">
          <frames>
            <DOMFrame index="0" keyMode="9728">
              <elements>
                <DOMShape isDrawingObject="true">
                  <matrix>
                    <Matrix a="0.99981689453125" d="0.861724853515625" tx="0.6" ty="51.25"/>
                  </matrix>
                  <fills>
                    <FillStyle index="1">
                      <SolidColor/>
                    </FillStyle>
                  </fills>
                  <edges>
                    <Edge fillStyle1="1" edges="
!17600 5525|17962 5472!17962 5472[18428 5393 18943 5269!18943 5269[18619 5638 17832 6022!17832 6022[17587 6141 17323 6248!17323 6248|17110 6331!17110 6331[16649 6702 15956 6919!15956 6919[15040 7206 13668 7251!13668 7251[13039 7272 13072
 6449!13072 6449[13098 5791 13544 4627!13544 4627[13863 3795 14359 2793!14359 2793[14607 2293 14792 1958!14792 1958[15842 2241 16741 2764!16741 2764[17006 2918 17311 3125!17311 3125[17589 3315 17637 3341!17637 3341[17815 3435 18325 3790
!18325 3790[18580 3967 18799 4125!18799 4125[19043 4224 19061 4455!19061 4455[19076 4636 18963 4826!18963 4826[18917 4901 18871 4942!18871 4942[18824 4982 18801 4967!18801 4967[18744 4927 18878 4609!18878 4609[18811 4579 18882 4483!18882
 4483[18900 4460 18889 4472!18889 4472[18859 4504 18786 4572!18786 4572|17600 5525"/>
                    <Edge cubics="!17600 5525(;17600,5525 18119,5468 18943,5269q17600 5525Q17600 5525q17962 5472Q18428 5393q18943 5269);"/>
                    <Edge cubics="!18943 5269(;18425,5860 17110,6331 17110,6331q18943 5269Q18619 5638q17832 6022Q17587 6141q17323 6248Q17110 6331q17110 6331);"/>
                    <Edge cubics="!17110 6331(;16603,6739 15686,7185 13668,7251q17110 6331Q16649 6702q15956 6919Q15040 7206q13668 7251);"/>
                    <Edge cubics="!14792 1958(;16480,2413 17354,3190 17637,3341q14792 1958Q15842 2241q16741 2764Q17006 2918q17311 3125Q17589 3315q17637 3341);"/>
                    <Edge cubics="!17637 3341(;17921,3492 18799,4125 18799,4125q17637 3341Q17815 3435q18325 3790Q18580 3967q18799 4125);"/>
                    <Edge cubics="!18799 4125(;19523,4419 18484,5538 18878,4609q18799 4125Q19043 4224q19061 4455Q19076 4636q18963 4826Q18917 4901q18871 4942Q18824 4982q18801 4967Q18744 4927q18878 4609);"/>
                    <Edge cubics="!18878 4609(;18758,4556 19037,4338 18786,4572q18878 4609Q18811 4579q18882 4483Q18900 4460q18889 4472Q18859 4504q18786 4572);"/>
                    <Edge cubics="!18786 4572(;18786,4572 17600,5525 17600,5525q18786 4572 17600 5525);"/>
                    <Edge cubics="!13668 7251(;11839,7311 14792,1958 14792,1958q13668 7251Q13039 7272q13072 6449Q13098 5791q13544 4627Q13863 3795q14359 2793Q14607 2293q14792 1958);"/>
                  </edges>
                </DOMShape>
                <DOMShape selected="true" isDrawingObject="true">
                  <matrix>
                    <Matrix a="0.786361694335938" d="0.861541748046875" tx="819.75" ty="234.65"/>
                  </matrix>
                  <fills>
                    <FillStyle index="1">
                      <SolidColor alpha="0.47843137254902"/>
                    </FillStyle>
                  </fills>
                  <edges>
                    <Edge fillStyle1="1" edges="
!272 17S2[443 -21 699 26!699 26[850 54 1212 156!1212 156[1590 263 1810 307!1810 307[2171 380 2492 379!2492 379[2553 379 2699 326!2699 326[2908 251 2963 236!2963 236[3306 140 3434 339!3434 339[2963 706 2519 896!2519 896[2384 953 2267 987
!2267 987[2182 1009 2187 1009!2187 1009|2213 1039!2213 1039[2255 1067 2342 1059!2342 1059[2617 1033 3223 655!3223 655[3525 466 3602 503!3602 503[3632 517 3650 572!3650 572[3683 669 3687 678!3687 678[3797 907 3154 1174!3154 1174[2680 1371
 1918 1547!1918 1547[1749 1585 1550 1620!1550 1620[1528 1612 1446 1566!1446 1566[1382 1529 1337 1527!1337 1527[834 1501 491 1275!491 1275[198 1083 72 786!72 786[-41 520 19 290!19 290[80 59 272 17"/>
                    <Edge cubics="!272 17(272,17;784,-96 1527,381 2492,379q272 17Q443 -21q699 26Q850 54q1212 156Q1590 263q1810 307Q2171 380q2492 379)2492,379;"/>
                    <Edge cubics="!2492 379(;2703,379 3223,10 3434,339q2492 379Q2553 379q2699 326Q2908 251q2963 236Q3306 140q3434 339);"/>
                    <Edge cubics="!3434 339(;2675,930 2168,1009 2187,1009q3434 339Q2963 706q2519 896Q2384 953q2267 987Q2182 1009q2187 1009);"/>
                    <Edge cubics="!2187 1009(;2187,1009 2254,1259 3223,655q2187 1009Q2187 1009q2213 1039Q2255 1067q2342 1059Q2617 1033q3223 655);"/>
                    <Edge cubics="!3223 655(;3686,366 3617,531 3687,678q3223 655Q3525 466q3602 503Q3632 517q3650 572Q3683 669q3687 678);"/>
                    <Edge cubics="!3687 678(;3851,1020 2691,1368 1918,1547q3687 678Q3797 907q3154 1174Q2680 1371q1918 1547);"/>
                    <Edge cubics="!1918 1547(;1815,1570 1691,1595 1550,1620q1918 1547Q1749 1585q1550 1620);"/>
                    <Edge cubics="!1550 1620(;1478,1595 1415,1531 1337,1527q1550 1620Q1528 1612q1446 1566Q1382 1529q1337 1527);"/>
                    <Edge cubics="!1337 1527(;-104,1452 -241,129 272,17q1337 1527Q834 1501q491 1275Q198 1083q72 786Q-41 520q19 290Q80 59q272 17);"/>
                  </edges>
                </DOMShape>
              </elements>
            </DOMFrame>
          </frames>
        </DOMLayer>
      </layers>
    </DOMTimeline>
  </timeline>
</DOMSymbolItem>